elu_core/__init__.py
elu_core/lifecycle.py
elu_core/main.py
elu_core/communication/__init__.py
elu_core/communication/communication.py
elu_core/motor/__init__.py
elu_core/motor/motor.py
elu_core/motor/motor_controller.py
elu_core/motor/servo.py
elu_core/sensoric/__init__.py
elu_core/sensoric/emergency_stop/__init__.py
elu_core/sensoric/emergency_stop/emergency_stop.py
elu_core/sensoric/ultrasonic/__init__.py
elu_core/sensoric/ultrasonic/ultrasonic.py
elu_core-0.1.0.dist-info/LICENSE
elu_core-0.1.0.dist-info/METADATA
elu_core-0.1.0.dist-info/WHEEL
elu_core-0.1.0.dist-info/top_level.txt
elu_core-0.1.0.dist-info/RECORD
