Metadata-Version: 2.1
Name: elu-core
Version: 0.1.0
Summary: This package controls the hardware
Home-page: https://github.com/MaFa961/Eingebettete_Systeme_ELU_core
Author: Marcel F
Author-email: marcel.fasterding@gmx.de
License: UNKNOWN
Platform: UNKNOWN
Classifier: Programming Language :: Python :: 3
Classifier: License :: OSI Approved :: MIT License
Classifier: Operating System :: OS Independent
